jupyter_rospkg/__init__.py
jupyter_rospkg/_version.py
jupyter_rospkg/handlers.py
jupyter_rospkg/pkgs.py
jupyter_rospkg/config/jpserver-jupyter-rospkg.json
jupyter_rospkg/config/nbserver-jupyter-rospkg.json
jupyter_rospkg/tests/__init__.py
jupyter_rospkg/tests/test_handlers.py
jupyter_rospkg-0.3.0.data/data/etc/jupyter/jupyter_notebook_config.d/nbserver-jupyter-rospkg.json
jupyter_rospkg-0.3.0.data/data/etc/jupyter/jupyter_server_config.d/jpserver-jupyter-rospkg.json
jupyter_rospkg-0.3.0.dist-info/METADATA
jupyter_rospkg-0.3.0.dist-info/WHEEL
jupyter_rospkg-0.3.0.dist-info/licenses/LICENSE
jupyter_rospkg-0.3.0.dist-info/RECORD
