Metadata-Version: 2.1
Name: jupyter_rospkg
Version: 0.3.0
Summary: A server extension for JupyterLab to handle ROS packages
Project-URL: Homepage, https://github.com/ihuicatl/jupyter-rospkg
Author-email: Isabel Paredes <isabel.paredes@quantstack.net>
License: BSD 3-Clause License
License-File: LICENSE
Keywords: Jupyter,JupyterLab,JupyterLab3
Classifier: Framework :: Jupyter
Classifier: Framework :: Jupyter :: JupyterLab
Classifier: Framework :: Jupyter :: JupyterLab :: 3
Classifier: Framework :: Jupyter :: JupyterLab :: Extensions
Classifier: Framework :: Jupyter :: JupyterLab :: Extensions :: Prebuilt
Classifier: License :: OSI Approved :: BSD License
Classifier: Programming Language :: Python
Classifier: Programming Language :: Python :: 3
Classifier: Programming Language :: Python :: 3.7
Classifier: Programming Language :: Python :: 3.8
Classifier: Programming Language :: Python :: 3.9
Classifier: Programming Language :: Python :: 3.10
Requires-Python: >=3.7
Requires-Dist: jupyter-server<2,>=1.6
Requires-Dist: notebook
Requires-Dist: rospkg
Provides-Extra: test
Requires-Dist: coverage; extra == 'test'
Requires-Dist: pytest; extra == 'test'
Requires-Dist: pytest-asyncio; extra == 'test'
Requires-Dist: pytest-cov; extra == 'test'
Requires-Dist: pytest-tornasync; extra == 'test'
